LICENSE
MANIFEST.in
README.rst
setup.py
django_feedaggregator.egg-info/PKG-INFO
django_feedaggregator.egg-info/SOURCES.txt
django_feedaggregator.egg-info/dependency_links.txt
django_feedaggregator.egg-info/requires.txt
django_feedaggregator.egg-info/top_level.txt
docs/commands.rst
docs/configuration.rst
docs/index.rst
docs/installation.rst
docs/templatetags.rst
feedaggregator/__init__.py
feedaggregator/admin.py
feedaggregator/apps.py
feedaggregator/context_processors.py
feedaggregator/feeds.py
feedaggregator/managers.py
feedaggregator/models.py
feedaggregator/settings.py
feedaggregator/sitemaps.py
feedaggregator/tasks.py
feedaggregator/urls.py
feedaggregator/views.py
feedaggregator/static/feedaggregator/css/feedaggregator.css
feedaggregator/templates/.DS_Store
feedaggregator/templates/feedaggregator/.DS_Store
feedaggregator/templates/feedaggregator/_item.html
feedaggregator/templates/feedaggregator/_pagination.html
feedaggregator/templates/feedaggregator/base.html
feedaggregator/templates/feedaggregator/feed_detail.html
feedaggregator/templates/feedaggregator/feed_list.html
feedaggregator/templates/feedaggregator/item_detail.html
feedaggregator/templates/feedaggregator/item_list.html
feedaggregator/templates/feedaggregator/sidebar.html
feedaggregator/templates/feedaggregator/tag_cloud.html
feedaggregator/templates/feedaggregator/tag_detail.html
feedaggregator/templates/feedaggregator/tag_list.html
feedaggregator/templates/feedaggregator/export/opml.xml
feedaggregator/templates/feedaggregator/tags/feed_list.html
feedaggregator/templates/feedaggregator/tags/item_list.html
feedaggregator/templates/feedaggregator/tags/tag_list.html